README.md
asjson.py
setup.py
asjson.egg-info/PKG-INFO
asjson.egg-info/SOURCES.txt
asjson.egg-info/dependency_links.txt
asjson.egg-info/top_level.txt