Metadata-Version: 1.1
Name: asjson
Version: 3.0.0
Summary: json.dumps with datetime, date and bson.ObjectId support
Home-page: https://github.com/imbolc/asjson
Author: Imbolc
Author-email: imbolc@imbolc.name
License: ISC
Platform: UNKNOWN
Classifier: Development Status :: 4 - Beta
Classifier: Intended Audience :: Developers
Classifier: License :: OSI Approved :: ISC License (ISCL)
Classifier: Programming Language :: Python :: 3
